odoo9_addon_l10n_es_account_balance_report-9.0.1.0.0.99.dev5-py2.7-nspkg.pth
odoo9_addon_l10n_es_account_balance_report-9.0.1.0.0.99.dev5.dist-info/METADATA
odoo9_addon_l10n_es_account_balance_report-9.0.1.0.0.99.dev5.dist-info/RECORD
odoo9_addon_l10n_es_account_balance_report-9.0.1.0.0.99.dev5.dist-info/WHEEL
odoo9_addon_l10n_es_account_balance_report-9.0.1.0.0.99.dev5.dist-info/namespace_packages.txt
odoo9_addon_l10n_es_account_balance_report-9.0.1.0.0.99.dev5.dist-info/top_level.txt
odoo_addons/l10n_es_account_balance_report/README.rst
odoo_addons/l10n_es_account_balance_report/__init__.py
odoo_addons/l10n_es_account_balance_report/__openerp__.py
odoo_addons/l10n_es_account_balance_report/data/balance_abreviado.xml
odoo_addons/l10n_es_account_balance_report/data/balance_normal.xml
odoo_addons/l10n_es_account_balance_report/data/balance_pymes.xml
odoo_addons/l10n_es_account_balance_report/data/estado_ingresos_gastos_normal.xml
odoo_addons/l10n_es_account_balance_report/data/pyg_abreviado.xml
odoo_addons/l10n_es_account_balance_report/data/pyg_normal.xml
odoo_addons/l10n_es_account_balance_report/data/pyg_pymes.xml
odoo_addons/l10n_es_account_balance_report/i18n/ca.po
odoo_addons/l10n_es_account_balance_report/i18n/es.po
odoo_addons/l10n_es_account_balance_report/i18n/eu.po
odoo_addons/l10n_es_account_balance_report/i18n/gl.po
odoo_addons/l10n_es_account_balance_report/i18n/l10n_es_account_balance_report.pot
odoo_addons/l10n_es_account_balance_report/static/description/icon.png
