Metadata-Version: 2.1
Name: odoo9-addon-l10n-es-account-balance-report
Version: 9.0.1.0.0.99.dev5
Summary: Informes de cuentas anuales españoles
Home-page: http://www.pexego.es
Author: Pexego, Tecnativa,Zikzakmedia,Odoo Community Association (OCA)
Author-email: support@odoo-community.org
License: AGPL-3
Platform: UNKNOWN
Classifier: Programming Language :: Python
Classifier: Framework :: Odoo
Classifier: License :: OSI Approved :: GNU Affero General Public License v3
Requires-Python: ~=2.7
Requires-Dist: odoo9-addon-account-balance-reporting
Requires-Dist: odoo (<9.1a,>=9.0a)
